[
  {
    "start": 0.0,
    "end": 0.4,
    "similarity": 0.2452,
    "mask_score": 0.3477
  },
  {
    "start": 0.2,
    "end": 0.6,
    "similarity": 0.3592,
    "mask_score": 0.5138
  },
  {
    "start": 0.4,
    "end": 0.8,
    "similarity": 0.5261,
    "mask_score": 0.742
  },
  {
    "start": 0.6,
    "end": 1.0,
    "similarity": 0.5261,
    "mask_score": 0.742
  },
  {
    "start": 0.8,
    "end": 1.2,
    "similarity": 0.3785,
    "mask_score": 0.5426
  },
  {
    "start": 1.0,
    "end": 1.4,
    "similarity": 0.3666,
    "mask_score": 0.5249
  },
  {
    "start": 1.2,
    "end": 1.6,
    "similarity": 0.3666,
    "mask_score": 0.5249
  },
  {
    "start": 1.4,
    "end": 1.8,
    "similarity": 0.3883,
    "mask_score": 0.5572
  },
  {
    "start": 1.6,
    "end": 2.0,
    "similarity": 0.4631,
    "mask_score": 0.6634
  },
  {
    "start": 1.8,
    "end": 2.2,
    "similarity": 0.4631,
    "mask_score": 0.6634
  },
  {
    "start": 2.0,
    "end": 2.4,
    "similarity": 0.4295,
    "mask_score": 0.617
  },
  {
    "start": 2.2,
    "end": 2.6,
    "similarity": 0.355,
    "mask_score": 0.5075
  },
  {
    "start": 2.4,
    "end": 2.8,
    "similarity": 0.355,
    "mask_score": 0.5075
  },
  {
    "start": 2.6,
    "end": 3.0,
    "similarity": 0.1813,
    "mask_score": 0.2665
  },
  {
    "start": 2.8,
    "end": 3.2,
    "similarity": 0.1411,
    "mask_score": 0.2222
  },
  {
    "start": 3.0,
    "end": 3.4,
    "similarity": -0.0085,
    "mask_score": 0.1042
  },
  {
    "start": 3.2,
    "end": 3.6,
    "similarity": -0.0085,
    "mask_score": 0.1042
  },
  {
    "start": 3.4,
    "end": 3.8,
    "similarity": 0.1161,
    "mask_score": 0.1973
  },
  {
    "start": 3.6,
    "end": 4.0,
    "similarity": 0.1161,
    "mask_score": 0.1973
  },
  {
    "start": 3.8,
    "end": 4.2,
    "similarity": 0.1167,
    "mask_score": 0.1978
  },
  {
    "start": 4.0,
    "end": 4.4,
    "similarity": 0.0569,
    "mask_score": 0.1469
  },
  {
    "start": 4.2,
    "end": 4.6,
    "similarity": 0.0569,
    "mask_score": 0.1469
  },
  {
    "start": 4.4,
    "end": 4.8,
    "similarity": 0.0345,
    "mask_score": 0.1309
  },
  {
    "start": 4.6,
    "end": 5.0,
    "similarity": -0.0791,
    "mask_score": 0.0708
  },
  {
    "start": 4.8,
    "end": 5.2,
    "similarity": -0.0791,
    "mask_score": 0.0708
  },
  {
    "start": 5.0,
    "end": 5.4,
    "similarity": 0.0712,
    "mask_score": 0.158
  },
  {
    "start": 5.2,
    "end": 5.6,
    "similarity": 0.0712,
    "mask_score": 0.158
  },
  {
    "start": 5.4,
    "end": 5.8,
    "similarity": 0.0691,
    "mask_score": 0.1564
  },
  {
    "start": 5.6,
    "end": 6.0,
    "similarity": 0.0603,
    "mask_score": 0.1496
  },
  {
    "start": 5.8,
    "end": 6.2,
    "similarity": 0.0603,
    "mask_score": 0.1496
  },
  {
    "start": 6.0,
    "end": 6.4,
    "similarity": 0.1166,
    "mask_score": 0.1977
  },
  {
    "start": 6.2,
    "end": 6.6,
    "similarity": 0.1166,
    "mask_score": 0.1977
  },
  {
    "start": 6.4,
    "end": 6.8,
    "similarity": 0.0449,
    "mask_score": 0.1382
  },
  {
    "start": 6.6,
    "end": 7.0,
    "similarity": 0.0123,
    "mask_score": 0.1165
  },
  {
    "start": 6.8,
    "end": 7.2,
    "similarity": 0.0173,
    "mask_score": 0.1196
  },
  {
    "start": 7.0,
    "end": 7.4,
    "similarity": 0.0123,
    "mask_score": 0.1165
  },
  {
    "start": 7.2,
    "end": 7.6,
    "similarity": 0.0031,
    "mask_score": 0.1109
  },
  {
    "start": 7.4,
    "end": 7.8,
    "similarity": 0.0031,
    "mask_score": 0.1109
  },
  {
    "start": 7.6,
    "end": 8.0,
    "similarity": 0.0461,
    "mask_score": 0.139
  },
  {
    "start": 7.8,
    "end": 8.2,
    "similarity": 0.0461,
    "mask_score": 0.139
  },
  {
    "start": 8.0,
    "end": 8.4,
    "similarity": 0.0114,
    "mask_score": 0.1159
  },
  {
    "start": 8.2,
    "end": 8.6,
    "similarity": 0.0114,
    "mask_score": 0.1159
  },
  {
    "start": 8.4,
    "end": 8.8,
    "similarity": 0.0004,
    "mask_score": 0.1093
  },
  {
    "start": 8.6,
    "end": 9.0,
    "similarity": -0.0207,
    "mask_score": 0.0976
  },
  {
    "start": 8.8,
    "end": 9.2,
    "similarity": -0.0474,
    "mask_score": 0.0844
  },
  {
    "start": 9.0,
    "end": 9.4,
    "similarity": -0.0207,
    "mask_score": 0.0976
  },
  {
    "start": 9.2,
    "end": 9.6,
    "similarity": -0.0099,
    "mask_score": 0.1034
  },
  {
    "start": 9.4,
    "end": 9.8,
    "similarity": 0.0023,
    "mask_score": 0.1104
  },
  {
    "start": 9.6,
    "end": 10.0,
    "similarity": 0.0023,
    "mask_score": 0.1104
  },
  {
    "start": 9.8,
    "end": 10.2,
    "similarity": 0.0066,
    "mask_score": 0.113
  },
  {
    "start": 10.0,
    "end": 10.4,
    "similarity": 0.0066,
    "mask_score": 0.113
  },
  {
    "start": 10.2,
    "end": 10.6,
    "similarity": 0.0577,
    "mask_score": 0.1476
  },
  {
    "start": 10.4,
    "end": 10.8,
    "similarity": 0.0577,
    "mask_score": 0.1476
  },
  {
    "start": 10.6,
    "end": 11.0,
    "similarity": 0.0577,
    "mask_score": 0.1476
  },
  {
    "start": 10.8,
    "end": 11.2,
    "similarity": 0.0705,
    "mask_score": 0.1575
  },
  {
    "start": 11.0,
    "end": 11.4,
    "similarity": 0.0884,
    "mask_score": 0.1723
  },
  {
    "start": 11.2,
    "end": 11.6,
    "similarity": 0.099,
    "mask_score": 0.1815
  },
  {
    "start": 11.4,
    "end": 11.8,
    "similarity": 0.099,
    "mask_score": 0.1815
  },
  {
    "start": 11.6,
    "end": 12.0,
    "similarity": -0.0506,
    "mask_score": 0.0829
  },
  {
    "start": 11.8,
    "end": 12.2,
    "similarity": -0.0506,
    "mask_score": 0.0829
  },
  {
    "start": 12.0,
    "end": 12.4,
    "similarity": 0.0119,
    "mask_score": 0.1162
  },
  {
    "start": 12.2,
    "end": 12.6,
    "similarity": 0.1215,
    "mask_score": 0.2025
  },
  {
    "start": 12.4,
    "end": 12.8,
    "similarity": 0.1411,
    "mask_score": 0.2221
  },
  {
    "start": 12.6,
    "end": 13.0,
    "similarity": 0.2229,
    "mask_score": 0.3181
  },
  {
    "start": 12.8,
    "end": 13.2,
    "similarity": 0.2306,
    "mask_score": 0.3282
  },
  {
    "start": 13.0,
    "end": 13.4,
    "similarity": 0.2306,
    "mask_score": 0.3282
  },
  {
    "start": 13.2,
    "end": 13.6,
    "similarity": 0.2134,
    "mask_score": 0.3058
  },
  {
    "start": 13.4,
    "end": 13.8,
    "similarity": 0.1716,
    "mask_score": 0.2553
  },
  {
    "start": 13.6,
    "end": 14.0,
    "similarity": 0.1248,
    "mask_score": 0.2057
  },
  {
    "start": 13.8,
    "end": 14.2,
    "similarity": -0.025,
    "mask_score": 0.0953
  },
  {
    "start": 14.0,
    "end": 14.4,
    "similarity": -0.025,
    "mask_score": 0.0953
  },
  {
    "start": 14.2,
    "end": 14.6,
    "similarity": 0.0245,
    "mask_score": 0.1243
  },
  {
    "start": 14.4,
    "end": 14.8,
    "similarity": 0.0375,
    "mask_score": 0.1329
  },
  {
    "start": 14.6,
    "end": 15.0,
    "similarity": 0.0603,
    "mask_score": 0.1496
  },
  {
    "start": 14.8,
    "end": 15.2,
    "similarity": 0.0818,
    "mask_score": 0.1667
  },
  {
    "start": 15.0,
    "end": 15.4,
    "similarity": 0.0603,
    "mask_score": 0.1496
  },
  {
    "start": 15.2,
    "end": 15.6,
    "similarity": 0.0818,
    "mask_score": 0.1667
  },
  {
    "start": 15.4,
    "end": 15.8,
    "similarity": 0.0587,
    "mask_score": 0.1483
  },
  {
    "start": 15.6,
    "end": 16.0,
    "similarity": 0.0852,
    "mask_score": 0.1696
  },
  {
    "start": 15.8,
    "end": 16.2,
    "similarity": 0.0667,
    "mask_score": 0.1545
  },
  {
    "start": 16.0,
    "end": 16.4,
    "similarity": 0.0667,
    "mask_score": 0.1545
  },
  {
    "start": 16.2,
    "end": 16.6,
    "similarity": 0.0667,
    "mask_score": 0.1545
  },
  {
    "start": 16.4,
    "end": 16.8,
    "similarity": 0.1442,
    "mask_score": 0.2253
  },
  {
    "start": 16.6,
    "end": 17.0,
    "similarity": 0.1442,
    "mask_score": 0.2253
  },
  {
    "start": 16.8,
    "end": 17.2,
    "similarity": 0.0369,
    "mask_score": 0.1326
  },
  {
    "start": 17.0,
    "end": 17.4,
    "similarity": 0.0369,
    "mask_score": 0.1326
  },
  {
    "start": 17.2,
    "end": 17.6,
    "similarity": 0.1595,
    "mask_score": 0.2418
  },
  {
    "start": 17.4,
    "end": 17.8,
    "similarity": 0.1595,
    "mask_score": 0.2418
  },
  {
    "start": 17.6,
    "end": 18.0,
    "similarity": 0.0872,
    "mask_score": 0.1713
  },
  {
    "start": 17.8,
    "end": 18.2,
    "similarity": 0.0872,
    "mask_score": 0.1713
  },
  {
    "start": 18.0,
    "end": 18.4,
    "similarity": 0.1187,
    "mask_score": 0.1998
  },
  {
    "start": 18.2,
    "end": 18.6,
    "similarity": 0.1559,
    "mask_score": 0.2378
  },
  {
    "start": 18.4,
    "end": 18.8,
    "similarity": 0.1714,
    "mask_score": 0.2551
  },
  {
    "start": 18.6,
    "end": 19.0,
    "similarity": 0.1845,
    "mask_score": 0.2703
  },
  {
    "start": 18.8,
    "end": 19.2,
    "similarity": 0.1845,
    "mask_score": 0.2703
  },
  {
    "start": 19.0,
    "end": 19.4,
    "similarity": 0.1845,
    "mask_score": 0.2703
  },
  {
    "start": 19.2,
    "end": 19.6,
    "similarity": 0.2268,
    "mask_score": 0.3232
  },
  {
    "start": 19.4,
    "end": 19.8,
    "similarity": 0.231,
    "mask_score": 0.3287
  },
  {
    "start": 19.6,
    "end": 20.0,
    "similarity": 0.2604,
    "mask_score": 0.3687
  },
  {
    "start": 19.8,
    "end": 20.2,
    "similarity": 0.2604,
    "mask_score": 0.3687
  },
  {
    "start": 20.0,
    "end": 20.4,
    "similarity": 0.0427,
    "mask_score": 0.1366
  },
  {
    "start": 20.2,
    "end": 20.6,
    "similarity": -0.0115,
    "mask_score": 0.1026
  },
  {
    "start": 20.4,
    "end": 20.8,
    "similarity": -0.0115,
    "mask_score": 0.1026
  },
  {
    "start": 20.6,
    "end": 21.0,
    "similarity": 0.0153,
    "mask_score": 0.1184
  },
  {
    "start": 20.8,
    "end": 21.2,
    "similarity": 0.0635,
    "mask_score": 0.152
  },
  {
    "start": 21.0,
    "end": 21.4,
    "similarity": 0.1387,
    "mask_score": 0.2197
  },
  {
    "start": 21.2,
    "end": 21.6,
    "similarity": 0.1387,
    "mask_score": 0.2197
  },
  {
    "start": 21.4,
    "end": 21.8,
    "similarity": 0.1349,
    "mask_score": 0.2158
  },
  {
    "start": 21.6,
    "end": 22.0,
    "similarity": 0.0925,
    "mask_score": 0.1758
  },
  {
    "start": 21.8,
    "end": 22.2,
    "similarity": 0.0281,
    "mask_score": 0.1266
  },
  {
    "start": 22.0,
    "end": 22.4,
    "similarity": 0.0152,
    "mask_score": 0.1183
  },
  {
    "start": 22.2,
    "end": 22.6,
    "similarity": 0.0281,
    "mask_score": 0.1266
  },
  {
    "start": 22.4,
    "end": 22.8,
    "similarity": 0.0442,
    "mask_score": 0.1377
  },
  {
    "start": 22.6,
    "end": 23.0,
    "similarity": 0.1847,
    "mask_score": 0.2706
  },
  {
    "start": 22.8,
    "end": 23.2,
    "similarity": 0.1879,
    "mask_score": 0.2744
  },
  {
    "start": 23.0,
    "end": 23.4,
    "similarity": 0.1879,
    "mask_score": 0.2744
  },
  {
    "start": 23.2,
    "end": 23.6,
    "similarity": 0.1121,
    "mask_score": 0.1935
  },
  {
    "start": 23.4,
    "end": 23.8,
    "similarity": 0.0372,
    "mask_score": 0.1328
  },
  {
    "start": 23.6,
    "end": 24.0,
    "similarity": 0.0004,
    "mask_score": 0.1093
  },
  {
    "start": 23.8,
    "end": 24.2,
    "similarity": 0.0004,
    "mask_score": 0.1093
  },
  {
    "start": 24.0,
    "end": 24.4,
    "similarity": -0.0076,
    "mask_score": 0.1048
  },
  {
    "start": 24.2,
    "end": 24.6,
    "similarity": -0.0326,
    "mask_score": 0.0915
  },
  {
    "start": 24.4,
    "end": 24.8,
    "similarity": -0.0076,
    "mask_score": 0.1048
  },
  {
    "start": 24.6,
    "end": 25.0,
    "similarity": -0.0114,
    "mask_score": 0.1026
  },
  {
    "start": 24.8,
    "end": 25.2,
    "similarity": 0.0254,
    "mask_score": 0.1248
  },
  {
    "start": 25.0,
    "end": 25.4,
    "similarity": 0.006,
    "mask_score": 0.1126
  },
  {
    "start": 25.2,
    "end": 25.6,
    "similarity": 0.0196,
    "mask_score": 0.121
  },
  {
    "start": 25.4,
    "end": 25.8,
    "similarity": 0.0195,
    "mask_score": 0.121
  },
  {
    "start": 25.6,
    "end": 26.0,
    "similarity": 0.0196,
    "mask_score": 0.121
  },
  {
    "start": 25.8,
    "end": 26.2,
    "similarity": 0.0195,
    "mask_score": 0.121
  },
  {
    "start": 26.0,
    "end": 26.4,
    "similarity": -0.017,
    "mask_score": 0.0996
  },
  {
    "start": 26.2,
    "end": 26.6,
    "similarity": -0.017,
    "mask_score": 0.0996
  },
  {
    "start": 26.4,
    "end": 26.8,
    "similarity": -0.0208,
    "mask_score": 0.0975
  },
  {
    "start": 26.6,
    "end": 27.0,
    "similarity": 0.037,
    "mask_score": 0.1326
  },
  {
    "start": 26.8,
    "end": 27.2,
    "similarity": 0.0241,
    "mask_score": 0.124
  },
  {
    "start": 27.0,
    "end": 27.4,
    "similarity": 0.0241,
    "mask_score": 0.124
  },
  {
    "start": 27.2,
    "end": 27.6,
    "similarity": 0.0241,
    "mask_score": 0.124
  },
  {
    "start": 27.4,
    "end": 27.8,
    "similarity": 0.1268,
    "mask_score": 0.2076
  },
  {
    "start": 27.6,
    "end": 28.0,
    "similarity": 0.1298,
    "mask_score": 0.2107
  },
  {
    "start": 27.8,
    "end": 28.2,
    "similarity": 0.1268,
    "mask_score": 0.2076
  },
  {
    "start": 28.0,
    "end": 28.4,
    "similarity": 0.0379,
    "mask_score": 0.1333
  },
  {
    "start": 28.2,
    "end": 28.6,
    "similarity": -0.0377,
    "mask_score": 0.089
  },
  {
    "start": 28.4,
    "end": 28.8,
    "similarity": -0.0541,
    "mask_score": 0.0813
  },
  {
    "start": 28.6,
    "end": 29.0,
    "similarity": -0.0541,
    "mask_score": 0.0813
  },
  {
    "start": 28.8,
    "end": 29.2,
    "similarity": 0.0199,
    "mask_score": 0.1213
  },
  {
    "start": 29.0,
    "end": 29.4,
    "similarity": 0.0355,
    "mask_score": 0.1316
  },
  {
    "start": 29.2,
    "end": 29.6,
    "similarity": 0.0742,
    "mask_score": 0.1605
  },
  {
    "start": 29.4,
    "end": 29.8,
    "similarity": 0.1514,
    "mask_score": 0.2329
  },
  {
    "start": 29.6,
    "end": 30.0,
    "similarity": 0.1514,
    "mask_score": 0.2329
  },
  {
    "start": 29.8,
    "end": 30.2,
    "similarity": 0.0803,
    "mask_score": 0.1654
  },
  {
    "start": 30.0,
    "end": 30.4,
    "similarity": 0.0488,
    "mask_score": 0.141
  },
  {
    "start": 30.2,
    "end": 30.6,
    "similarity": -0.0917,
    "mask_score": 0.066
  },
  {
    "start": 30.4,
    "end": 30.8,
    "similarity": -0.0917,
    "mask_score": 0.066
  },
  {
    "start": 30.6,
    "end": 31.0,
    "similarity": 0.0481,
    "mask_score": 0.1404
  },
  {
    "start": 30.8,
    "end": 31.2,
    "similarity": 0.0481,
    "mask_score": 0.1404
  },
  {
    "start": 31.0,
    "end": 31.4,
    "similarity": 0.0033,
    "mask_score": 0.111
  },
  {
    "start": 31.2,
    "end": 31.6,
    "similarity": -0.0226,
    "mask_score": 0.0966
  },
  {
    "start": 31.4,
    "end": 31.8,
    "similarity": -0.0582,
    "mask_score": 0.0795
  },
  {
    "start": 31.6,
    "end": 32.0,
    "similarity": -0.0582,
    "mask_score": 0.0795
  },
  {
    "start": 31.8,
    "end": 32.2,
    "similarity": -0.0415,
    "mask_score": 0.0872
  },
  {
    "start": 32.0,
    "end": 32.4,
    "similarity": 0.0432,
    "mask_score": 0.1369
  },
  {
    "start": 32.2,
    "end": 32.6,
    "similarity": 0.0775,
    "mask_score": 0.1631
  },
  {
    "start": 32.4,
    "end": 32.8,
    "similarity": 0.1731,
    "mask_score": 0.2571
  },
  {
    "start": 32.6,
    "end": 33.0,
    "similarity": 0.3431,
    "mask_score": 0.4897
  },
  {
    "start": 32.8,
    "end": 33.2,
    "similarity": 0.3553,
    "mask_score": 0.5079
  },
  {
    "start": 33.0,
    "end": 33.4,
    "similarity": 0.3776,
    "mask_score": 0.5413
  },
  {
    "start": 33.2,
    "end": 33.6,
    "similarity": 0.3553,
    "mask_score": 0.5079
  },
  {
    "start": 33.4,
    "end": 33.8,
    "similarity": 0.2419,
    "mask_score": 0.3434
  },
  {
    "start": 33.6,
    "end": 34.0,
    "similarity": 0.2419,
    "mask_score": 0.3434
  },
  {
    "start": 33.8,
    "end": 34.2,
    "similarity": 0.2961,
    "mask_score": 0.4198
  },
  {
    "start": 34.0,
    "end": 34.4,
    "similarity": 0.3482,
    "mask_score": 0.4973
  },
  {
    "start": 34.2,
    "end": 34.6,
    "similarity": 0.2961,
    "mask_score": 0.4198
  },
  {
    "start": 34.4,
    "end": 34.8,
    "similarity": 0.2055,
    "mask_score": 0.2959
  },
  {
    "start": 34.6,
    "end": 35.0,
    "similarity": 0.2055,
    "mask_score": 0.2959
  },
  {
    "start": 34.8,
    "end": 35.2,
    "similarity": 0.2432,
    "mask_score": 0.3451
  },
  {
    "start": 35.0,
    "end": 35.4,
    "similarity": 0.2453,
    "mask_score": 0.3479
  },
  {
    "start": 35.2,
    "end": 35.6,
    "similarity": 0.2859,
    "mask_score": 0.405
  },
  {
    "start": 35.4,
    "end": 35.8,
    "similarity": 0.2859,
    "mask_score": 0.405
  },
  {
    "start": 35.6,
    "end": 36.0,
    "similarity": 0.2504,
    "mask_score": 0.3549
  },
  {
    "start": 35.8,
    "end": 36.2,
    "similarity": 0.2504,
    "mask_score": 0.3549
  },
  {
    "start": 36.0,
    "end": 36.4,
    "similarity": 0.2975,
    "mask_score": 0.4219
  },
  {
    "start": 36.2,
    "end": 36.6,
    "similarity": 0.2975,
    "mask_score": 0.4219
  },
  {
    "start": 36.4,
    "end": 36.8,
    "similarity": 0.1495,
    "mask_score": 0.2309
  },
  {
    "start": 36.6,
    "end": 37.0,
    "similarity": 0.1425,
    "mask_score": 0.2236
  },
  {
    "start": 36.8,
    "end": 37.2,
    "similarity": 0.1341,
    "mask_score": 0.215
  },
  {
    "start": 37.0,
    "end": 37.4,
    "similarity": 0.0681,
    "mask_score": 0.1556
  },
  {
    "start": 37.2,
    "end": 37.6,
    "similarity": 0.0048,
    "mask_score": 0.1119
  },
  {
    "start": 37.4,
    "end": 37.8,
    "similarity": 0.0048,
    "mask_score": 0.1119
  },
  {
    "start": 37.6,
    "end": 38.0,
    "similarity": -0.0547,
    "mask_score": 0.081
  },
  {
    "start": 37.8,
    "end": 38.2,
    "similarity": -0.0359,
    "mask_score": 0.0898
  },
  {
    "start": 38.0,
    "end": 38.4,
    "similarity": -0.0359,
    "mask_score": 0.0898
  },
  {
    "start": 38.2,
    "end": 38.6,
    "similarity": -0.0343,
    "mask_score": 0.0907
  },
  {
    "start": 38.4,
    "end": 38.8,
    "similarity": 0.0754,
    "mask_score": 0.1614
  },
  {
    "start": 38.6,
    "end": 39.0,
    "similarity": 0.0754,
    "mask_score": 0.1614
  },
  {
    "start": 38.8,
    "end": 39.2,
    "similarity": 0.0535,
    "mask_score": 0.1444
  },
  {
    "start": 39.0,
    "end": 39.4,
    "similarity": 0.0535,
    "mask_score": 0.1444
  },
  {
    "start": 39.2,
    "end": 39.6,
    "similarity": 0.0606,
    "mask_score": 0.1497
  },
  {
    "start": 39.4,
    "end": 39.8,
    "similarity": 0.062,
    "mask_score": 0.1509
  },
  {
    "start": 39.6,
    "end": 40.0,
    "similarity": 0.062,
    "mask_score": 0.1509
  },
  {
    "start": 39.8,
    "end": 40.2,
    "similarity": 0.062,
    "mask_score": 0.1509
  },
  {
    "start": 40.0,
    "end": 40.4,
    "similarity": 0.1125,
    "mask_score": 0.1939
  },
  {
    "start": 40.2,
    "end": 40.6,
    "similarity": 0.0109,
    "mask_score": 0.1156
  },
  {
    "start": 40.4,
    "end": 40.8,
    "similarity": 0.0109,
    "mask_score": 0.1156
  },
  {
    "start": 40.6,
    "end": 41.0,
    "similarity": -0.0712,
    "mask_score": 0.074
  },
  {
    "start": 40.8,
    "end": 41.2,
    "similarity": -0.0712,
    "mask_score": 0.074
  },
  {
    "start": 41.0,
    "end": 41.4,
    "similarity": 0.0157,
    "mask_score": 0.1186
  },
  {
    "start": 41.2,
    "end": 41.6,
    "similarity": 0.0365,
    "mask_score": 0.1323
  },
  {
    "start": 41.4,
    "end": 41.8,
    "similarity": 0.0578,
    "mask_score": 0.1476
  },
  {
    "start": 41.6,
    "end": 42.0,
    "similarity": 0.085,
    "mask_score": 0.1694
  },
  {
    "start": 41.8,
    "end": 42.2,
    "similarity": 0.0608,
    "mask_score": 0.15
  },
  {
    "start": 42.0,
    "end": 42.4,
    "similarity": 0.1262,
    "mask_score": 0.2071
  },
  {
    "start": 42.2,
    "end": 42.6,
    "similarity": 0.0608,
    "mask_score": 0.15
  },
  {
    "start": 42.4,
    "end": 42.8,
    "similarity": 0.141,
    "mask_score": 0.222
  },
  {
    "start": 42.6,
    "end": 43.0,
    "similarity": 0.0453,
    "mask_score": 0.1384
  },
  {
    "start": 42.8,
    "end": 43.2,
    "similarity": 0.0603,
    "mask_score": 0.1495
  },
  {
    "start": 43.0,
    "end": 43.4,
    "similarity": 0.0453,
    "mask_score": 0.1384
  },
  {
    "start": 43.2,
    "end": 43.6,
    "similarity": 0.0252,
    "mask_score": 0.1247
  },
  {
    "start": 43.4,
    "end": 43.8,
    "similarity": 0.0252,
    "mask_score": 0.1247
  },
  {
    "start": 43.6,
    "end": 44.0,
    "similarity": 0.0549,
    "mask_score": 0.1455
  },
  {
    "start": 43.8,
    "end": 44.2,
    "similarity": 0.0549,
    "mask_score": 0.1455
  },
  {
    "start": 44.0,
    "end": 44.4,
    "similarity": 0.0176,
    "mask_score": 0.1198
  },
  {
    "start": 44.2,
    "end": 44.6,
    "similarity": 0.0089,
    "mask_score": 0.1144
  },
  {
    "start": 44.4,
    "end": 44.8,
    "similarity": 0.0089,
    "mask_score": 0.1144
  },
  {
    "start": 44.6,
    "end": 45.0,
    "similarity": 0.0089,
    "mask_score": 0.1144
  },
  {
    "start": 44.8,
    "end": 45.2,
    "similarity": 0.0039,
    "mask_score": 0.1114
  },
  {
    "start": 45.0,
    "end": 45.4,
    "similarity": 0.0039,
    "mask_score": 0.1114
  },
  {
    "start": 45.2,
    "end": 45.6,
    "similarity": 0.1106,
    "mask_score": 0.1921
  },
  {
    "start": 45.4,
    "end": 45.8,
    "similarity": 0.1106,
    "mask_score": 0.1921
  },
  {
    "start": 45.6,
    "end": 46.0,
    "similarity": 0.1106,
    "mask_score": 0.1921
  },
  {
    "start": 45.8,
    "end": 46.2,
    "similarity": 0.0644,
    "mask_score": 0.1527
  },
  {
    "start": 46.0,
    "end": 46.4,
    "similarity": 0.0715,
    "mask_score": 0.1583
  },
  {
    "start": 46.2,
    "end": 46.6,
    "similarity": 0.0715,
    "mask_score": 0.1583
  },
  {
    "start": 46.4,
    "end": 46.8,
    "similarity": 0.1542,
    "mask_score": 0.236
  },
  {
    "start": 46.6,
    "end": 47.0,
    "similarity": 0.1542,
    "mask_score": 0.236
  },
  {
    "start": 46.8,
    "end": 47.2,
    "similarity": 0.1224,
    "mask_score": 0.2033
  },
  {
    "start": 47.0,
    "end": 47.4,
    "similarity": 0.0645,
    "mask_score": 0.1528
  },
  {
    "start": 47.2,
    "end": 47.6,
    "similarity": 0.1224,
    "mask_score": 0.2033
  },
  {
    "start": 47.4,
    "end": 47.8,
    "similarity": 0.0645,
    "mask_score": 0.1528
  },
  {
    "start": 47.6,
    "end": 48.0,
    "similarity": 0.0026,
    "mask_score": 0.1106
  },
  {
    "start": 47.8,
    "end": 48.2,
    "similarity": -0.0197,
    "mask_score": 0.0981
  },
  {
    "start": 48.0,
    "end": 48.4,
    "similarity": -0.0381,
    "mask_score": 0.0888
  },
  {
    "start": 48.2,
    "end": 48.6,
    "similarity": -0.0578,
    "mask_score": 0.0797
  },
  {
    "start": 48.4,
    "end": 48.8,
    "similarity": -0.0698,
    "mask_score": 0.0745
  },
  {
    "start": 48.6,
    "end": 49.0,
    "similarity": -0.0578,
    "mask_score": 0.0797
  },
  {
    "start": 48.8,
    "end": 49.2,
    "similarity": 0.0196,
    "mask_score": 0.1211
  },
  {
    "start": 49.0,
    "end": 49.4,
    "similarity": 0.0256,
    "mask_score": 0.1249
  },
  {
    "start": 49.2,
    "end": 49.6,
    "similarity": 0.0707,
    "mask_score": 0.1577
  },
  {
    "start": 49.4,
    "end": 49.8,
    "similarity": 0.0869,
    "mask_score": 0.171
  },
  {
    "start": 49.6,
    "end": 50.0,
    "similarity": 0.1095,
    "mask_score": 0.1911
  },
  {
    "start": 49.8,
    "end": 50.2,
    "similarity": 0.1095,
    "mask_score": 0.1911
  },
  {
    "start": 50.0,
    "end": 50.4,
    "similarity": 0.1019,
    "mask_score": 0.1842
  },
  {
    "start": 50.2,
    "end": 50.6,
    "similarity": 0.0901,
    "mask_score": 0.1738
  },
  {
    "start": 50.4,
    "end": 50.8,
    "similarity": 0.072,
    "mask_score": 0.1587
  },
  {
    "start": 50.6,
    "end": 51.0,
    "similarity": 0.0535,
    "mask_score": 0.1444
  },
  {
    "start": 50.8,
    "end": 51.2,
    "similarity": 0.072,
    "mask_score": 0.1587
  },
  {
    "start": 51.0,
    "end": 51.4,
    "similarity": 0.0553,
    "mask_score": 0.1458
  },
  {
    "start": 51.2,
    "end": 51.6,
    "similarity": 0.0991,
    "mask_score": 0.1817
  },
  {
    "start": 51.4,
    "end": 51.8,
    "similarity": 0.0553,
    "mask_score": 0.1458
  },
  {
    "start": 51.6,
    "end": 52.0,
    "similarity": 0.0642,
    "mask_score": 0.1526
  },
  {
    "start": 51.8,
    "end": 52.2,
    "similarity": 0.0219,
    "mask_score": 0.1226
  },
  {
    "start": 52.0,
    "end": 52.4,
    "similarity": 0.0356,
    "mask_score": 0.1316
  },
  {
    "start": 52.2,
    "end": 52.6,
    "similarity": 0.0356,
    "mask_score": 0.1316
  },
  {
    "start": 52.4,
    "end": 52.8,
    "similarity": 0.2035,
    "mask_score": 0.2933
  },
  {
    "start": 52.6,
    "end": 53.0,
    "similarity": 0.2136,
    "mask_score": 0.3061
  },
  {
    "start": 52.8,
    "end": 53.2,
    "similarity": 0.3418,
    "mask_score": 0.4876
  },
  {
    "start": 53.0,
    "end": 53.4,
    "similarity": 0.3418,
    "mask_score": 0.4876
  },
  {
    "start": 53.2,
    "end": 53.6,
    "similarity": 0.2416,
    "mask_score": 0.3429
  },
  {
    "start": 53.4,
    "end": 53.8,
    "similarity": 0.2416,
    "mask_score": 0.3429
  },
  {
    "start": 53.6,
    "end": 54.0,
    "similarity": 0.2762,
    "mask_score": 0.391
  },
  {
    "start": 53.8,
    "end": 54.2,
    "similarity": 0.2762,
    "mask_score": 0.391
  },
  {
    "start": 54.0,
    "end": 54.4,
    "similarity": 0.2228,
    "mask_score": 0.3179
  },
  {
    "start": 54.2,
    "end": 54.6,
    "similarity": 0.2228,
    "mask_score": 0.3179
  },
  {
    "start": 54.4,
    "end": 54.8,
    "similarity": 0.3256,
    "mask_score": 0.4635
  },
  {
    "start": 54.6,
    "end": 55.0,
    "similarity": 0.3292,
    "mask_score": 0.4688
  },
  {
    "start": 54.8,
    "end": 55.2,
    "similarity": 0.3256,
    "mask_score": 0.4635
  },
  {
    "start": 55.0,
    "end": 55.4,
    "similarity": 0.2281,
    "mask_score": 0.3248
  },
  {
    "start": 55.2,
    "end": 55.6,
    "similarity": 0.1484,
    "mask_score": 0.2298
  },
  {
    "start": 55.4,
    "end": 55.8,
    "similarity": 0.1484,
    "mask_score": 0.2298
  },
  {
    "start": 55.6,
    "end": 56.0,
    "similarity": 0.0598,
    "mask_score": 0.1492
  },
  {
    "start": 55.8,
    "end": 56.2,
    "similarity": 0.0598,
    "mask_score": 0.1492
  },
  {
    "start": 56.0,
    "end": 56.4,
    "similarity": 0.2709,
    "mask_score": 0.3835
  },
  {
    "start": 56.2,
    "end": 56.6,
    "similarity": 0.2709,
    "mask_score": 0.3835
  },
  {
    "start": 56.4,
    "end": 56.8,
    "similarity": 0.2013,
    "mask_score": 0.2906
  },
  {
    "start": 56.6,
    "end": 57.0,
    "similarity": 0.2013,
    "mask_score": 0.2906
  },
  {
    "start": 56.8,
    "end": 57.2,
    "similarity": 0.2013,
    "mask_score": 0.2906
  },
  {
    "start": 57.0,
    "end": 57.4,
    "similarity": 0.1829,
    "mask_score": 0.2685
  },
  {
    "start": 57.2,
    "end": 57.6,
    "similarity": 0.08,
    "mask_score": 0.1652
  },
  {
    "start": 57.4,
    "end": 57.8,
    "similarity": 0.0537,
    "mask_score": 0.1446
  },
  {
    "start": 57.6,
    "end": 58.0,
    "similarity": 0.0697,
    "mask_score": 0.1569
  },
  {
    "start": 57.8,
    "end": 58.2,
    "similarity": 0.0537,
    "mask_score": 0.1446
  },
  {
    "start": 58.0,
    "end": 58.4,
    "similarity": 0.0697,
    "mask_score": 0.1569
  },
  {
    "start": 58.2,
    "end": 58.6,
    "similarity": 0.0182,
    "mask_score": 0.1202
  },
  {
    "start": 58.4,
    "end": 58.8,
    "similarity": 0.0493,
    "mask_score": 0.1413
  },
  {
    "start": 58.6,
    "end": 59.0,
    "similarity": 0.0493,
    "mask_score": 0.1413
  },
  {
    "start": 58.8,
    "end": 59.2,
    "similarity": 0.0493,
    "mask_score": 0.1413
  },
  {
    "start": 59.0,
    "end": 59.4,
    "similarity": 0.0657,
    "mask_score": 0.1537
  },
  {
    "start": 59.2,
    "end": 59.6,
    "similarity": 0.0483,
    "mask_score": 0.1406
  },
  {
    "start": 59.4,
    "end": 59.8,
    "similarity": 0.0483,
    "mask_score": 0.1406
  },
  {
    "start": 59.6,
    "end": 60.0,
    "similarity": 0.0121,
    "mask_score": 0.1163
  },
  {
    "start": 59.8,
    "end": 60.2,
    "similarity": 0.0121,
    "mask_score": 0.1163
  },
  {
    "start": 60.0,
    "end": 60.4,
    "similarity": 0.0445,
    "mask_score": 0.1379
  },
  {
    "start": 60.2,
    "end": 60.6,
    "similarity": 0.0445,
    "mask_score": 0.1379
  },
  {
    "start": 60.4,
    "end": 60.8,
    "similarity": 0.0213,
    "mask_score": 0.1221
  },
  {
    "start": 60.6,
    "end": 61.0,
    "similarity": 0.0213,
    "mask_score": 0.1221
  },
  {
    "start": 60.8,
    "end": 61.2,
    "similarity": 0.0295,
    "mask_score": 0.1275
  },
  {
    "start": 61.0,
    "end": 61.4,
    "similarity": 0.0403,
    "mask_score": 0.1349
  },
  {
    "start": 61.2,
    "end": 61.6,
    "similarity": 0.1619,
    "mask_score": 0.2445
  },
  {
    "start": 61.4,
    "end": 61.8,
    "similarity": 0.3351,
    "mask_score": 0.4776
  },
  {
    "start": 61.6,
    "end": 62.0,
    "similarity": 0.3849,
    "mask_score": 0.5521
  },
  {
    "start": 61.8,
    "end": 62.2,
    "similarity": 0.3849,
    "mask_score": 0.5521
  },
  {
    "start": 62.0,
    "end": 62.4,
    "similarity": 0.1795,
    "mask_score": 0.2645
  },
  {
    "start": 62.2,
    "end": 62.6,
    "similarity": 0.1795,
    "mask_score": 0.2645
  },
  {
    "start": 62.4,
    "end": 62.8,
    "similarity": 0.3629,
    "mask_score": 0.5194
  },
  {
    "start": 62.6,
    "end": 63.0,
    "similarity": 0.3629,
    "mask_score": 0.5194
  },
  {
    "start": 62.8,
    "end": 63.2,
    "similarity": 0.3395,
    "mask_score": 0.4842
  },
  {
    "start": 63.0,
    "end": 63.4,
    "similarity": 0.276,
    "mask_score": 0.3908
  },
  {
    "start": 63.2,
    "end": 63.6,
    "similarity": 0.2842,
    "mask_score": 0.4026
  },
  {
    "start": 63.4,
    "end": 63.8,
    "similarity": 0.2479,
    "mask_score": 0.3514
  },
  {
    "start": 63.6,
    "end": 64.0,
    "similarity": 0.2479,
    "mask_score": 0.3514
  },
  {
    "start": 63.8,
    "end": 64.2,
    "similarity": 0.1947,
    "mask_score": 0.2826
  },
  {
    "start": 64.0,
    "end": 64.4,
    "similarity": 0.1947,
    "mask_score": 0.2826
  },
  {
    "start": 64.2,
    "end": 64.6,
    "similarity": 0.2114,
    "mask_score": 0.3033
  },
  {
    "start": 64.4,
    "end": 64.8,
    "similarity": 0.2266,
    "mask_score": 0.3229
  },
  {
    "start": 64.6,
    "end": 65.0,
    "similarity": 0.2807,
    "mask_score": 0.3976
  },
  {
    "start": 64.8,
    "end": 65.2,
    "similarity": 0.2807,
    "mask_score": 0.3976
  },
  {
    "start": 65.0,
    "end": 65.4,
    "similarity": 0.2807,
    "mask_score": 0.3976
  },
  {
    "start": 65.2,
    "end": 65.6,
    "similarity": 0.2173,
    "mask_score": 0.3109
  },
  {
    "start": 65.4,
    "end": 65.8,
    "similarity": 0.2108,
    "mask_score": 0.3026
  },
  {
    "start": 65.6,
    "end": 66.0,
    "similarity": 0.2108,
    "mask_score": 0.3026
  },
  {
    "start": 65.8,
    "end": 66.2,
    "similarity": 0.2164,
    "mask_score": 0.3097
  },
  {
    "start": 66.0,
    "end": 66.4,
    "similarity": 0.2164,
    "mask_score": 0.3097
  },
  {
    "start": 66.2,
    "end": 66.6,
    "similarity": 0.0945,
    "mask_score": 0.1775
  },
  {
    "start": 66.4,
    "end": 66.8,
    "similarity": 0.0945,
    "mask_score": 0.1775
  },
  {
    "start": 66.6,
    "end": 67.0,
    "similarity": 0.0945,
    "mask_score": 0.1775
  },
  {
    "start": 66.8,
    "end": 67.2,
    "similarity": 0.0308,
    "mask_score": 0.1284
  },
  {
    "start": 67.0,
    "end": 67.4,
    "similarity": 0.0308,
    "mask_score": 0.1284
  },
  {
    "start": 67.2,
    "end": 67.6,
    "similarity": 0.0358,
    "mask_score": 0.1318
  },
  {
    "start": 67.4,
    "end": 67.8,
    "similarity": 0.0787,
    "mask_score": 0.1641
  },
  {
    "start": 67.6,
    "end": 68.0,
    "similarity": 0.0787,
    "mask_score": 0.1641
  },
  {
    "start": 67.8,
    "end": 68.2,
    "similarity": 0.0407,
    "mask_score": 0.1352
  },
  {
    "start": 68.0,
    "end": 68.4,
    "similarity": 0.0225,
    "mask_score": 0.123
  },
  {
    "start": 68.2,
    "end": 68.6,
    "similarity": 0.0176,
    "mask_score": 0.1198
  },
  {
    "start": 68.4,
    "end": 68.8,
    "similarity": 0.0225,
    "mask_score": 0.123
  },
  {
    "start": 68.6,
    "end": 69.0,
    "similarity": 0.0176,
    "mask_score": 0.1198
  },
  {
    "start": 68.8,
    "end": 69.2,
    "similarity": 0.0792,
    "mask_score": 0.1645
  },
  {
    "start": 69.0,
    "end": 69.4,
    "similarity": -0.0012,
    "mask_score": 0.1084
  },
  {
    "start": 69.2,
    "end": 69.6,
    "similarity": 0.0786,
    "mask_score": 0.1641
  },
  {
    "start": 69.4,
    "end": 69.8,
    "similarity": -0.0012,
    "mask_score": 0.1084
  },
  {
    "start": 69.6,
    "end": 70.0,
    "similarity": -0.0067,
    "mask_score": 0.1052
  },
  {
    "start": 69.8,
    "end": 70.2,
    "similarity": -0.0067,
    "mask_score": 0.1052
  },
  {
    "start": 70.0,
    "end": 70.4,
    "similarity": -0.0032,
    "mask_score": 0.1072
  },
  {
    "start": 70.2,
    "end": 70.6,
    "similarity": 0.0558,
    "mask_score": 0.1461
  },
  {
    "start": 70.4,
    "end": 70.8,
    "similarity": 0.0558,
    "mask_score": 0.1461
  },
  {
    "start": 70.6,
    "end": 71.0,
    "similarity": 0.0452,
    "mask_score": 0.1383
  },
  {
    "start": 70.8,
    "end": 71.2,
    "similarity": 0.0452,
    "mask_score": 0.1383
  },
  {
    "start": 71.0,
    "end": 71.4,
    "similarity": 0.0452,
    "mask_score": 0.1383
  },
  {
    "start": 71.2,
    "end": 71.6,
    "similarity": 0.0318,
    "mask_score": 0.1291
  },
  {
    "start": 71.4,
    "end": 71.8,
    "similarity": 0.0318,
    "mask_score": 0.1291
  },
  {
    "start": 71.6,
    "end": 72.0,
    "similarity": 0.0313,
    "mask_score": 0.1287
  },
  {
    "start": 71.8,
    "end": 72.2,
    "similarity": -0.089,
    "mask_score": 0.067
  },
  {
    "start": 72.0,
    "end": 72.4,
    "similarity": -0.089,
    "mask_score": 0.067
  },
  {
    "start": 72.2,
    "end": 72.6,
    "similarity": 0.0801,
    "mask_score": 0.1653
  },
  {
    "start": 72.4,
    "end": 72.8,
    "similarity": 0.0801,
    "mask_score": 0.1653
  },
  {
    "start": 72.6,
    "end": 73.0,
    "similarity": 0.0801,
    "mask_score": 0.1653
  },
  {
    "start": 72.8,
    "end": 73.2,
    "similarity": 0.0656,
    "mask_score": 0.1536
  },
  {
    "start": 73.0,
    "end": 73.4,
    "similarity": 0.0656,
    "mask_score": 0.1536
  },
  {
    "start": 73.2,
    "end": 73.6,
    "similarity": 0.0656,
    "mask_score": 0.1536
  },
  {
    "start": 73.4,
    "end": 73.8,
    "similarity": 0.0763,
    "mask_score": 0.1622
  },
  {
    "start": 73.6,
    "end": 74.0,
    "similarity": 0.1402,
    "mask_score": 0.2212
  },
  {
    "start": 73.8,
    "end": 74.2,
    "similarity": 0.1402,
    "mask_score": 0.2212
  },
  {
    "start": 74.0,
    "end": 74.4,
    "similarity": 0.0674,
    "mask_score": 0.155
  },
  {
    "start": 74.2,
    "end": 74.6,
    "similarity": 0.0569,
    "mask_score": 0.1469
  },
  {
    "start": 74.4,
    "end": 74.8,
    "similarity": 0.0629,
    "mask_score": 0.1515
  },
  {
    "start": 74.6,
    "end": 75.0,
    "similarity": 0.0569,
    "mask_score": 0.1469
  },
  {
    "start": 74.8,
    "end": 75.2,
    "similarity": 0.0629,
    "mask_score": 0.1515
  },
  {
    "start": 75.0,
    "end": 75.4,
    "similarity": 0.1352,
    "mask_score": 0.216
  },
  {
    "start": 75.2,
    "end": 75.6,
    "similarity": 0.444,
    "mask_score": 0.6374
  },
  {
    "start": 75.4,
    "end": 75.8,
    "similarity": 0.444,
    "mask_score": 0.6374
  },
  {
    "start": 75.6,
    "end": 76.0,
    "similarity": 0.2893,
    "mask_score": 0.4099
  },
  {
    "start": 75.8,
    "end": 76.2,
    "similarity": 0.2399,
    "mask_score": 0.3407
  },
  {
    "start": 76.0,
    "end": 76.4,
    "similarity": 0.1985,
    "mask_score": 0.2872
  },
  {
    "start": 76.2,
    "end": 76.6,
    "similarity": 0.1985,
    "mask_score": 0.2872
  },
  {
    "start": 76.4,
    "end": 76.8,
    "similarity": 0.2457,
    "mask_score": 0.3485
  },
  {
    "start": 76.6,
    "end": 77.0,
    "similarity": 0.2837,
    "mask_score": 0.4019
  },
  {
    "start": 76.8,
    "end": 77.2,
    "similarity": 0.2837,
    "mask_score": 0.4019
  },
  {
    "start": 77.0,
    "end": 77.4,
    "similarity": 0.2579,
    "mask_score": 0.3653
  },
  {
    "start": 77.2,
    "end": 77.6,
    "similarity": 0.2579,
    "mask_score": 0.3653
  },
  {
    "start": 77.4,
    "end": 77.8,
    "similarity": 0.2764,
    "mask_score": 0.3914
  },
  {
    "start": 77.6,
    "end": 78.0,
    "similarity": 0.2764,
    "mask_score": 0.3914
  },
  {
    "start": 77.8,
    "end": 78.2,
    "similarity": 0.2859,
    "mask_score": 0.4051
  },
  {
    "start": 78.0,
    "end": 78.4,
    "similarity": 0.3121,
    "mask_score": 0.4434
  },
  {
    "start": 78.2,
    "end": 78.6,
    "similarity": 0.3121,
    "mask_score": 0.4434
  },
  {
    "start": 78.4,
    "end": 78.8,
    "similarity": 0.2107,
    "mask_score": 0.3025
  },
  {
    "start": 78.6,
    "end": 79.0,
    "similarity": 0.2107,
    "mask_score": 0.3025
  },
  {
    "start": 78.8,
    "end": 79.2,
    "similarity": 0.2827,
    "mask_score": 0.4005
  },
  {
    "start": 79.0,
    "end": 79.4,
    "similarity": 0.3084,
    "mask_score": 0.4379
  },
  {
    "start": 79.2,
    "end": 79.6,
    "similarity": 0.2827,
    "mask_score": 0.4005
  },
  {
    "start": 79.4,
    "end": 79.8,
    "similarity": 0.1655,
    "mask_score": 0.2484
  },
  {
    "start": 79.6,
    "end": 80.0,
    "similarity": 0.1473,
    "mask_score": 0.2286
  },
  {
    "start": 79.8,
    "end": 80.2,
    "similarity": 0.1655,
    "mask_score": 0.2484
  },
  {
    "start": 80.0,
    "end": 80.4,
    "similarity": 0.2411,
    "mask_score": 0.3423
  },
  {
    "start": 80.2,
    "end": 80.6,
    "similarity": 0.2411,
    "mask_score": 0.3423
  },
  {
    "start": 80.4,
    "end": 80.8,
    "similarity": 0.217,
    "mask_score": 0.3104
  },
  {
    "start": 80.6,
    "end": 81.0,
    "similarity": -0.0143,
    "mask_score": 0.1011
  },
  {
    "start": 80.8,
    "end": 81.2,
    "similarity": -0.0252,
    "mask_score": 0.0952
  },
  {
    "start": 81.0,
    "end": 81.4,
    "similarity": -0.0301,
    "mask_score": 0.0927
  },
  {
    "start": 81.2,
    "end": 81.6,
    "similarity": -0.0301,
    "mask_score": 0.0927
  },
  {
    "start": 81.4,
    "end": 81.8,
    "similarity": -0.0153,
    "mask_score": 0.1005
  },
  {
    "start": 81.6,
    "end": 82.0,
    "similarity": 0.0399,
    "mask_score": 0.1347
  },
  {
    "start": 81.8,
    "end": 82.2,
    "similarity": 0.0605,
    "mask_score": 0.1497
  },
  {
    "start": 82.0,
    "end": 82.4,
    "similarity": 0.0399,
    "mask_score": 0.1347
  },
  {
    "start": 82.2,
    "end": 82.6,
    "similarity": 0.0605,
    "mask_score": 0.1497
  },
  {
    "start": 82.4,
    "end": 82.8,
    "similarity": 0.0312,
    "mask_score": 0.1287
  },
  {
    "start": 82.6,
    "end": 83.0,
    "similarity": 0.0888,
    "mask_score": 0.1726
  },
  {
    "start": 82.8,
    "end": 83.2,
    "similarity": 0.044,
    "mask_score": 0.1375
  },
  {
    "start": 83.0,
    "end": 83.4,
    "similarity": 0.044,
    "mask_score": 0.1375
  },
  {
    "start": 83.2,
    "end": 83.6,
    "similarity": -0.0104,
    "mask_score": 0.1032
  },
  {
    "start": 83.4,
    "end": 83.8,
    "similarity": -0.0104,
    "mask_score": 0.1032
  },
  {
    "start": 83.6,
    "end": 84.0,
    "similarity": 0.0021,
    "mask_score": 0.1103
  },
  {
    "start": 83.8,
    "end": 84.2,
    "similarity": 0.0132,
    "mask_score": 0.117
  },
  {
    "start": 84.0,
    "end": 84.4,
    "similarity": 0.0948,
    "mask_score": 0.1778
  },
  {
    "start": 84.2,
    "end": 84.6,
    "similarity": 0.1124,
    "mask_score": 0.1938
  },
  {
    "start": 84.4,
    "end": 84.8,
    "similarity": 0.1217,
    "mask_score": 0.2027
  },
  {
    "start": 84.6,
    "end": 85.0,
    "similarity": 0.1274,
    "mask_score": 0.2083
  },
  {
    "start": 84.8,
    "end": 85.2,
    "similarity": 0.1274,
    "mask_score": 0.2083
  },
  {
    "start": 85.0,
    "end": 85.4,
    "similarity": 0.0747,
    "mask_score": 0.1609
  },
  {
    "start": 85.2,
    "end": 85.6,
    "similarity": 0.0747,
    "mask_score": 0.1609
  },
  {
    "start": 85.4,
    "end": 85.8,
    "similarity": 0.0773,
    "mask_score": 0.163
  },
  {
    "start": 85.6,
    "end": 86.0,
    "similarity": 0.1105,
    "mask_score": 0.192
  },
  {
    "start": 85.8,
    "end": 86.2,
    "similarity": 0.0773,
    "mask_score": 0.163
  },
  {
    "start": 86.0,
    "end": 86.4,
    "similarity": 0.0961,
    "mask_score": 0.1789
  },
  {
    "start": 86.2,
    "end": 86.6,
    "similarity": 0.0961,
    "mask_score": 0.1789
  },
  {
    "start": 86.4,
    "end": 86.8,
    "similarity": 0.0961,
    "mask_score": 0.1789
  },
  {
    "start": 86.6,
    "end": 87.0,
    "similarity": 0.0334,
    "mask_score": 0.1301
  },
  {
    "start": 86.8,
    "end": 87.2,
    "similarity": 0.0334,
    "mask_score": 0.1301
  },
  {
    "start": 87.0,
    "end": 87.4,
    "similarity": 0.0747,
    "mask_score": 0.1608
  },
  {
    "start": 87.2,
    "end": 87.6,
    "similarity": 0.0747,
    "mask_score": 0.1608
  },
  {
    "start": 87.4,
    "end": 87.8,
    "similarity": 0.0876,
    "mask_score": 0.1716
  },
  {
    "start": 87.6,
    "end": 88.0,
    "similarity": 0.1282,
    "mask_score": 0.2091
  },
  {
    "start": 87.8,
    "end": 88.2,
    "similarity": 0.1361,
    "mask_score": 0.217
  },
  {
    "start": 88.0,
    "end": 88.4,
    "similarity": 0.1898,
    "mask_score": 0.2766
  },
  {
    "start": 88.2,
    "end": 88.6,
    "similarity": 0.2105,
    "mask_score": 0.3021
  },
  {
    "start": 88.4,
    "end": 88.8,
    "similarity": 0.2337,
    "mask_score": 0.3323
  },
  {
    "start": 88.6,
    "end": 89.0,
    "similarity": 0.2562,
    "mask_score": 0.3629
  },
  {
    "start": 88.8,
    "end": 89.2,
    "similarity": 0.2562,
    "mask_score": 0.3629
  },
  {
    "start": 89.0,
    "end": 89.4,
    "similarity": 0.1594,
    "mask_score": 0.2417
  },
  {
    "start": 89.2,
    "end": 89.6,
    "similarity": 0.1209,
    "mask_score": 0.2019
  },
  {
    "start": 89.4,
    "end": 89.8,
    "similarity": 0.1209,
    "mask_score": 0.2019
  },
  {
    "start": 89.6,
    "end": 90.0,
    "similarity": 0.0202,
    "mask_score": 0.1215
  },
  {
    "start": 89.8,
    "end": 90.2,
    "similarity": 0.1247,
    "mask_score": 0.2055
  },
  {
    "start": 90.0,
    "end": 90.4,
    "similarity": 0.2671,
    "mask_score": 0.3781
  },
  {
    "start": 90.2,
    "end": 90.6,
    "similarity": 0.2739,
    "mask_score": 0.3878
  },
  {
    "start": 90.4,
    "end": 90.8,
    "similarity": 0.2739,
    "mask_score": 0.3878
  },
  {
    "start": 90.6,
    "end": 91.0,
    "similarity": 0.2739,
    "mask_score": 0.3878
  },
  {
    "start": 90.8,
    "end": 91.2,
    "similarity": 0.116,
    "mask_score": 0.1972
  },
  {
    "start": 91.0,
    "end": 91.4,
    "similarity": 0.0207,
    "mask_score": 0.1218
  },
  {
    "start": 91.2,
    "end": 91.556,
    "similarity": 0.0207,
    "mask_score": 0.1218
  },
  {
    "start": 91.4,
    "end": 91.556,
    "similarity": 0.1125,
    "mask_score": 0.1939
  }
]